[
  {
    "line": 2,
    "elements": [
      {
        "line": 3,
        "name": "User goes to employee page clicks to my operations and clicks to manage Customers",
        "description": "",
        "type": "background",
        "keyword": "Background",
        "steps": []
      },
      {
        "start_timestamp": "2020-11-16T04:55:16.269Z",
        "line": 4,
        "name": "TC01 All customers should show up on manage customers module populating the account information of the customer \"First Name  Last Name  Middle Initial  Email  Mobile Phone Number  Phone Number  Address  Create Date \"",
        "description": "",
        "id": "an-employee-can-manage-customer;tc01-all-customers-should-show-up-on-manage-customers-module-populating-the-account-information-of-the-customer-\"first-name--last-name--middle-initial--email--mobile-phone-number--phone-number--address--create-date-\"",
        "type": "scenario",
        "keyword": "Scenario",
        "steps": [
          {
            "result": {
              "status": "undefined"
            },
            "line": 5,
            "name": "user is on manage customer page",
            "match": {},
            "keyword": "Given "
          },
          {
            "result": {
              "status": "undefined"
            },
            "line": 6,
            "name": "get the web table header",
            "match": {},
            "keyword": "And "
          },
          {
            "result": {
              "status": "undefined"
            },
            "line": 7,
            "name": "verify the table header contains \"First Name\"  \"Last Name\"  \"Middle Initial\"  \"Email\"  \"Mobile Phone Number\"  \"Phone Number\"  \"Address\"  \"Create Date\"",
            "match": {},
            "keyword": "Then "
          }
        ],
        "tags": [
          {
            "name": "@tableHeaderCustomers"
          }
        ]
      }
    ],
    "name": "An Employee can manage Customer",
    "description": "",
    "id": "an-employee-can-manage-customer",
    "keyword": "Feature",
    "uri": "file:src/test/resources/features/US_012EmployeeCanManageCustomer.feature",
    "tags": [
      {
        "name": "@tableHeaderCustomers",
        "type": "Tag",
        "location": {
          "line": 1,
          "column": 1
        }
      }
    ]
  }
]